allmetal3d/__init__.py
allmetal3d/allmetal3d.py
allmetal3d/command_line.py
allmetal3d/frontend/frontend_novacancy.py
allmetal3d/frontend/script_novacancy.js
allmetal3d/frontend/vue.js
allmetal3d/utils/constants.py
allmetal3d/utils/helpersNew.py
allmetal3d/utils/main.py
allmetal3d/utils/model.py
allmetal3d/utils/voxelizationNew.py
allmetal3d-0.7.3.dist-info/LICENSE
allmetal3d-0.7.3.dist-info/METADATA
allmetal3d-0.7.3.dist-info/WHEEL
allmetal3d-0.7.3.dist-info/entry_points.txt
allmetal3d-0.7.3.dist-info/RECORD
